chibi_hybrid/__init__.py
chibi_hybrid/chibi_hybrid.py
chibi_hybrid-1.2.1.dist-info/AUTHORS.rst
chibi_hybrid-1.2.1.dist-info/LICENSE
chibi_hybrid-1.2.1.dist-info/METADATA
chibi_hybrid-1.2.1.dist-info/WHEEL
chibi_hybrid-1.2.1.dist-info/top_level.txt
chibi_hybrid-1.2.1.dist-info/RECORD
