Metadata-Version: 2.1
Name: chibi_hybrid
Version: 1.2.1
Summary: simple class for have hybrid class and instance methods
Home-page: https://github.com/dem4ply/chibi_hybrid
Author: Dem4ply
Author-email: dem4ply@gmail.com
Keywords: chibi_hybrid
Classifier: Development Status :: 2 - Pre-Alpha
Classifier: Intended Audience :: Developers
Classifier: Natural Language :: English
Classifier: Programming Language :: Python :: 3
Classifier: Programming Language :: Python :: 3.5
Classifier: Programming Language :: Python :: 3.6
Classifier: Programming Language :: Python :: 3.7
Classifier: Programming Language :: Python :: 3.8
Requires-Python: >=2.7, !=3.0.*, !=3.1.*, !=3.2.*, !=3.3.*, !=3.4.*
License-File: LICENSE
License-File: AUTHORS.rst
